[
    {
        "character": "橙",
        "creator": "国文学研究資料館",
        "delegate": true,
        "id": "U+6A59_200021763_00042_1_X2058_Y1902",
        "link": "https://lab.nijl.ac.jp/jikei/viewer/?manifest=https://lab.nijl.ac.jp/jikei/api/biblio/200021763/%E6%A9%99/manifest&pos=82&xywh=2058,1902,203,275",
        "manifest_url": "https://lab.nijl.ac.jp/jikei/api/char/U+6A59_200021763_00042_1_X2058_Y1902/manifest",
        "rights": "『日本古典籍くずし字データセット』（国文研ほか所蔵／CODH加工） doi:10.20676/00000340",
        "rights_url": "https://creativecommons.org/licenses/by-sa/4.0/deed.ja",
        "source": {
            "bid": "200021763",
            "frame": 42,
            "label": "『膳部料理抄』（200021763）42r",
            "side": "r",
            "title": "膳部料理抄"
        },
        "subject": "日本古典籍くずし字データ",
        "thumbnail_url": "https://lab.nijl.ac.jp/jikei/iiif/200021763/characters/U+6A59/U+6A59_200021763_00042_1_X2058_Y1902.jpg/full/full/0/default.jpg",
        "unicode": "6A59"
    },
    {
        "character": "橙",
        "creator": "国文学研究資料館",
        "delegate": true,
        "id": "U+6A59_200021925_00013_2_X1443_Y0997",
        "link": "https://lab.nijl.ac.jp/jikei/viewer/?manifest=https://lab.nijl.ac.jp/jikei/api/biblio/200021925/%E6%A9%99/manifest&pos=24&xywh=1443,997,115,113",
        "manifest_url": "https://lab.nijl.ac.jp/jikei/api/char/U+6A59_200021925_00013_2_X1443_Y0997/manifest",
        "rights": "『日本古典籍くずし字データセット』（国文研ほか所蔵／CODH加工） doi:10.20676/00000340",
        "rights_url": "https://creativecommons.org/licenses/by-sa/4.0/deed.ja",
        "source": {
            "bid": "200021925",
            "frame": 13,
            "label": "『新編異国料理』（200021925）13v",
            "side": "v",
            "title": "新編異国料理"
        },
        "subject": "日本古典籍くずし字データ",
        "thumbnail_url": "https://lab.nijl.ac.jp/jikei/iiif/200021925/characters/U+6A59/U+6A59_200021925_00013_2_X1443_Y0997.jpg/full/full/0/default.jpg",
        "unicode": "6A59"
    },
    {
        "character": "橙",
        "creator": "国文学研究資料館",
        "delegate": false,
        "id": "U+6A59_200021925_00013_2_X1497_Y1246",
        "link": "https://lab.nijl.ac.jp/jikei/viewer/?manifest=https://lab.nijl.ac.jp/jikei/api/biblio/200021925/%E6%A9%99/manifest&pos=24&xywh=1497,1246,68,76",
        "manifest_url": "https://lab.nijl.ac.jp/jikei/api/char/U+6A59_200021925_00013_2_X1497_Y1246/manifest",
        "rights": "『日本古典籍くずし字データセット』（国文研ほか所蔵／CODH加工） doi:10.20676/00000340",
        "rights_url": "https://creativecommons.org/licenses/by-sa/4.0/deed.ja",
        "source": {
            "bid": "200021925",
            "frame": 13,
            "label": "『新編異国料理』（200021925）13v",
            "side": "v",
            "title": "新編異国料理"
        },
        "subject": "日本古典籍くずし字データ",
        "thumbnail_url": "https://lab.nijl.ac.jp/jikei/iiif/200021925/characters/U+6A59/U+6A59_200021925_00013_2_X1497_Y1246.jpg/full/full/0/default.jpg",
        "unicode": "6A59"
    },
    {
        "character": "橙",
        "creator": "国文学研究資料館",
        "delegate": false,
        "id": "U+6A59_200021925_00018_1_X1245_Y1204",
        "link": "https://lab.nijl.ac.jp/jikei/viewer/?manifest=https://lab.nijl.ac.jp/jikei/api/biblio/200021925/%E6%A9%99/manifest&pos=33&xywh=1245,1204,88,76",
        "manifest_url": "https://lab.nijl.ac.jp/jikei/api/char/U+6A59_200021925_00018_1_X1245_Y1204/manifest",
        "rights": "『日本古典籍くずし字データセット』（国文研ほか所蔵／CODH加工） doi:10.20676/00000340",
        "rights_url": "https://creativecommons.org/licenses/by-sa/4.0/deed.ja",
        "source": {
            "bid": "200021925",
            "frame": 18,
            "label": "『新編異国料理』（200021925）18r",
            "side": "r",
            "title": "新編異国料理"
        },
        "subject": "日本古典籍くずし字データ",
        "thumbnail_url": "https://lab.nijl.ac.jp/jikei/iiif/200021925/characters/U+6A59/U+6A59_200021925_00018_1_X1245_Y1204.jpg/full/full/0/default.jpg",
        "unicode": "6A59"
    },
    {
        "character": "橙",
        "creator": "国文学研究資料館",
        "delegate": false,
        "id": "U+6A59_200021925_00021_1_X0205_Y0236",
        "link": "https://lab.nijl.ac.jp/jikei/viewer/?manifest=https://lab.nijl.ac.jp/jikei/api/biblio/200021925/%E6%A9%99/manifest&pos=39&xywh=205,236,109,104",
        "manifest_url": "https://lab.nijl.ac.jp/jikei/api/char/U+6A59_200021925_00021_1_X0205_Y0236/manifest",
        "rights": "『日本古典籍くずし字データセット』（国文研ほか所蔵／CODH加工） doi:10.20676/00000340",
        "rights_url": "https://creativecommons.org/licenses/by-sa/4.0/deed.ja",
        "source": {
            "bid": "200021925",
            "frame": 21,
            "label": "『新編異国料理』（200021925）21r",
            "side": "r",
            "title": "新編異国料理"
        },
        "subject": "日本古典籍くずし字データ",
        "thumbnail_url": "https://lab.nijl.ac.jp/jikei/iiif/200021925/characters/U+6A59/U+6A59_200021925_00021_1_X0205_Y0236.jpg/full/full/0/default.jpg",
        "unicode": "6A59"
    }
]